README.rst
setup.py
epub_extract_jpeg/__init__.py
epub_extract_jpeg/epub_extract_jpeg.py
epub_extract_jpeg.egg-info/PKG-INFO
epub_extract_jpeg.egg-info/SOURCES.txt
epub_extract_jpeg.egg-info/dependency_links.txt
epub_extract_jpeg.egg-info/entry_points.txt
epub_extract_jpeg.egg-info/top_level.txt