Metadata-Version: 1.0
Name: epub-extract-jpeg
Version: 0.6.2
Summary: Extract comic EPUB pages to Jpeg files.
Home-page: https://github.com/ytyng/epub-extract-jpeg.git
Author: ytyng
Author-email: ytyng@live.jp
License: BSD
Keywords: comic epub extract jpeg
Platform: UNKNOWN
